LICENSE
README.md
pyproject.toml
setup.py
./pymiau/__init__.py
./pymiau/data/miau.jpeg
pymiau.egg-info/PKG-INFO
pymiau.egg-info/SOURCES.txt
pymiau.egg-info/dependency_links.txt
pymiau.egg-info/entry_points.txt
pymiau.egg-info/requires.txt
pymiau.egg-info/top_level.txt