Metadata-Version: 2.1
Name: pymiau
Version: 0.3
Summary: Make a Miau
Home-page: https://pypi.org/project/pymiau
Author: Fulan@ de Tal
Author-email: fulano.de.tal@macondo.co
License: MIT
Keywords: Cats Dogs
Platform: UNKNOWN
Classifier: Programming Language :: Python :: 3
Classifier: License :: OSI Approved :: MIT License
Classifier: Operating System :: OS Independent
License-File: LICENSE
